LICENSE
MANIFEST.in
README.rst
setup.py
dashboard/__init__.py
dashboard/admin.py
dashboard/base.py
dashboard/models.py
dashboard/settings.py
dashboard/locale/ru/LC_MESSAGES/django.mo
dashboard/locale/ru/LC_MESSAGES/django.po
dashboard/static/dashboard/css/style.css
dashboard/static/dashboard/images/button-bg.png
dashboard/static/dashboard/images/dashboard-widget-bg.png
dashboard/static/dashboard/images/dashboard-widget-menu.png
dashboard/templates/admin/custom_dashboard_index.html
dashboard/templates/admin/index.html
dashboard/templates/dashboard/apps.html
dashboard/templates/dashboard/available_widgets.html
dashboard/templates/dashboard/dashboard.html
dashboard/templates/dashboard/help.html
dashboard/templates/dashboard/log.html
dashboard/templates/dashboard/tags/admin_app_list.html
dashboard/templatetags/__init__.py
dashboard/templatetags/dashboard.py
lemon_dashboard.egg-info/PKG-INFO
lemon_dashboard.egg-info/SOURCES.txt
lemon_dashboard.egg-info/dependency_links.txt
lemon_dashboard.egg-info/requires.txt
lemon_dashboard.egg-info/top_level.txt